wlr_layout_ui/__init__.py
wlr_layout_ui/displaywidget.py
wlr_layout_ui/factories.py
wlr_layout_ui/gui.py
wlr_layout_ui/profiles.py
wlr_layout_ui/screens.py
wlr_layout_ui/settings.py
wlr_layout_ui/shapes.py
wlr_layout_ui/types.py
wlr_layout_ui/utils.py
wlr_layout_ui/widgets.py
wlr_layout_ui-1.6.16.dist-info/LICENSE
wlr_layout_ui-1.6.16.dist-info/METADATA
wlr_layout_ui-1.6.16.dist-info/WHEEL
wlr_layout_ui-1.6.16.dist-info/entry_points.txt
wlr_layout_ui-1.6.16.dist-info/RECORD
