Metadata-Version: 2.3
Name: wlr-layout-ui
Version: 1.6.16
Summary: A tiny GUI to configure screen layouts on wayland
License: MIT
Author: fdev31
Author-email: fdev31@gmail.com
Requires-Python: >=3.8,<4.0
Classifier: License :: OSI Approved :: MIT License
Classifier: Programming Language :: Python :: 3
Classifier: Programming Language :: Python :: 3.8
Classifier: Programming Language :: Python :: 3.9
Classifier: Programming Language :: Python :: 3.10
Classifier: Programming Language :: Python :: 3.11
Classifier: Programming Language :: Python :: 3.12
Classifier: Programming Language :: Python :: 3.13
Requires-Dist: pyglet (>=2.0.0,<3.0.0)
Requires-Dist: tomli (>=2.0.1,<3.0.0)
Requires-Dist: tomli-w (>=1.0.0,<2.0.0)
Project-URL: Homepage, https://github.com/fdev31/wlr-layout-ui
